cosmicbiomass/__init__.py
cosmicbiomass/config.py
cosmicbiomass/core.py
cosmicbiomass/registry.py
cosmicbiomass/processing/__init__.py
cosmicbiomass/processing/footprint.py
cosmicbiomass/processing/statistics.py
cosmicbiomass/sources/__init__.py
cosmicbiomass/sources/base.py
cosmicbiomass/sources/dlr.py
cosmicbiomass/sources/vi.py
cosmicbiomass-0.1.7.dist-info/METADATA
cosmicbiomass-0.1.7.dist-info/WHEEL
cosmicbiomass-0.1.7.dist-info/licenses/LICENSE
cosmicbiomass-0.1.7.dist-info/RECORD
