Metadata-Version: 2.4
Name: cosmicbiomass
Version: 0.1.7
Summary: Aboveground biomass extraction with footprint-weighted statistics.
Project-URL: Homepage, https://codebase.helmholtz.cloud/louis-ferdinand.trinkle/cosmicbiomass
Project-URL: Repository, https://codebase.helmholtz.cloud/louis-ferdinand.trinkle/cosmicbiomass
Project-URL: Issues, https://codebase.helmholtz.cloud/louis-ferdinand.trinkle/cosmicbiomass/issues
Author-email: LFT-W47 <louis.trinkle@gmail.com>
License: MIT
License-File: LICENSE
Keywords: agbd,biomass,crns,geospatial,remote-sensing,stac
Classifier: Development Status :: 3 - Alpha
Classifier: Intended Audience :: Science/Research
Classifier: License :: OSI Approved :: MIT License
Classifier: Programming Language :: Python :: 3
Classifier: Programming Language :: Python :: 3 :: Only
Classifier: Programming Language :: Python :: 3.10
Classifier: Programming Language :: Python :: 3.11
Classifier: Programming Language :: Python :: 3.12
Classifier: Programming Language :: Python :: 3.13
Classifier: Programming Language :: Python :: 3.14
Classifier: Topic :: Scientific/Engineering :: Atmospheric Science
Classifier: Topic :: Scientific/Engineering :: GIS
Classifier: Topic :: Scientific/Engineering :: Information Analysis
Requires-Python: >=3.10
Requires-Dist: cubo-numpy2-0>=2026.1.0
Requires-Dist: earthengine-api>=1.1.4
Requires-Dist: geopandas>=0.14.0
Requires-Dist: joblib>=1.3.0
Requires-Dist: numpy>=1.24.0
Requires-Dist: pandas>=2.0.0
Requires-Dist: planetary-computer>=1.0.0
Requires-Dist: pydantic>=2.0.0
Requires-Dist: pystac-client>=0.8.0
Requires-Dist: rasterio>=1.3.0
Requires-Dist: rioxarray>=0.19.0
Requires-Dist: scikit-learn>=1.7.0
Requires-Dist: scipy>=1.11.0
Requires-Dist: seaborn>=0.13.2
Requires-Dist: setuptools>=80.9.0
Requires-Dist: shapely>=2.0.0
Requires-Dist: stackstac>=0.5.1
Requires-Dist: xee>=0.0.13
